<entry-sniffer>
    <id>63</id>
    <filename>sniffer.bin</filename>
    <version>
        <major>6</major>
        <minor>8</minor>
        <revision>67</revision>
    </version>
    <data>
        <str-tunarray-element>
            <fields>
                <str-tunarray-element>
                    <data-fieldset>
                        <real-float32>
                            <type>0</type>
                            <id>3100</id>
                            <scale>1.0</scale>
                        </real-float32>
                    </data-fieldset>
                </str-tunarray-element>
                <str-tunarray-element>
                    <data-fieldset>
                        <real-float32>
                            <type>0</type>
                            <id>3101</id>
                            <scale>1.0</scale>
                        </real-float32>
                    </data-fieldset>
                </str-tunarray-element>
                <str-tunarray-element>
                    <data-fieldset>
                        <real-float32>
                            <type>0</type>
                            <id>3102</id>
                            <scale>1.0</scale>
                        </real-float32>
                    </data-fieldset>
                </str-tunarray-element>
                <str-tunarray-element>
                    <data-fieldset>
                        <pos_abs>
                            <type>10</type>
                            <id>28672</id>
                        </pos_abs>
                    </data-fieldset>
                </str-tunarray-element>
                <str-tunarray-element>
                    <data-fieldset>
                        <real-float32>
                            <type>0</type>
                            <id>3103</id>
                            <scale>1.0</scale>
                        </real-float32>
                    </data-fieldset>
                </str-tunarray-element>
                <str-tunarray-element>
                    <data-fieldset>
                        <real-float32>
                            <type>0</type>
                            <id>3104</id>
                            <scale>1.0</scale>
                        </real-float32>
                    </data-fieldset>
                </str-tunarray-element>
            </fields>
            <pktmask>
                <uav>1408</uav>
            </pktmask>
            <map>
                <str-tunarray-element str-tunarray-key="0">
                    <data>
                        <type>0</type>
                        <id-in>3100</id-in>
                        <id-out>3101</id-out>
                    </data>
                </str-tunarray-element>
                <str-tunarray-element str-tunarray-key="1">
                    <data>
                        <type>0</type>
                        <id-in>3101</id-in>
                        <id-out>3102</id-out>
                    </data>
                </str-tunarray-element>
                <str-tunarray-element str-tunarray-key="2">
                    <data>
                        <type>0</type>
                        <id-in>3102</id-in>
                        <id-out>3105</id-out>
                    </data>
                </str-tunarray-element>
                <str-tunarray-element str-tunarray-key="3">
                    <data>
                        <type>11</type>
                        <id-in>28672</id-in>
                        <id-out>28672</id-out>
                    </data>
                </str-tunarray-element>
                <str-tunarray-element str-tunarray-key="4">
                    <data>
                        <type>0</type>
                        <id-in>3103</id-in>
                        <id-out>3109</id-out>
                    </data>
                </str-tunarray-element>
                <str-tunarray-element str-tunarray-key="5">
                    <data>
                        <type>0</type>
                        <id-in>3104</id-in>
                        <id-out>3108</id-out>
                    </data>
                </str-tunarray-element>
            </map>
            <accept_all>0</accept_all>
            <timeout>0.0</timeout>
        </str-tunarray-element>
    </data>
</entry-sniffer>
