<entry-automations-gname>
    <id>150</id>
    <filename>agname.bin</filename>
    <version>
        <major>6</major>
        <minor>12</minor>
        <revision>49</revision>
    </version>
    <data>
        <map>
            <str-tunarray-element str-tunarray-key="0">
                <data>
                    <string>Phase Buttons</string>
                </data>
            </str-tunarray-element>
            <str-tunarray-element str-tunarray-key="1">
                <data>
                    <string>Transitions</string>
                </data>
            </str-tunarray-element>
            <str-tunarray-element str-tunarray-key="2">
                <data>
                    <string>Stick</string>
                </data>
            </str-tunarray-element>
            <str-tunarray-element str-tunarray-key="3">
                <data>
                    <string>Failsafe</string>
                </data>
            </str-tunarray-element>
            <str-tunarray-element str-tunarray-key="4">
                <data>
                    <string>Integral Enable</string>
                </data>
            </str-tunarray-element>
            <str-tunarray-element str-tunarray-key="5">
                <data>
                    <string>Navigation</string>
                </data>
            </str-tunarray-element>
            <str-tunarray-element str-tunarray-key="6">
                <data>
                    <string>Home</string>
                </data>
            </str-tunarray-element>
            <str-tunarray-element str-tunarray-key="7">
                <data>
                    <string>Calibration</string>
                </data>
            </str-tunarray-element>
        </map>
    </data>
</entry-automations-gname>
